setup.cfg
setup.py
painter/__init__.py
painter/ansi_patterns.py
painter/ansi_styles.py
painter/painter.py
painter/strip_color.py
painter/strip_color_cli.py
painter/supports_color.py
painter.egg-info/PKG-INFO
painter.egg-info/SOURCES.txt
painter.egg-info/dependency_links.txt
painter.egg-info/entry_points.txt
painter.egg-info/not-zip-safe
painter.egg-info/top_level.txt